c14n/Canonicalize.py
c14n/NumberToJson.py
c14n/__init__.py
pyld/__about__.py
pyld/__init__.py
pyld/context_resolver.py
pyld/jsonld.py
pyld/resolved_context.py
pyld/documentloader/__init__.py
pyld/documentloader/aiohttp.py
pyld/documentloader/requests.py
OT_PyLD-2.1.1.dist-info/LICENSE
OT_PyLD-2.1.1.dist-info/METADATA
OT_PyLD-2.1.1.dist-info/WHEEL
OT_PyLD-2.1.1.dist-info/top_level.txt
OT_PyLD-2.1.1.dist-info/RECORD
