Metadata-Version: 2.1
Name: OT-PyLD
Version: 2.1.1
Summary: Python implementation of the JSON-LD API
Home-page: https://github.com/OriginTrail/pyld
Author: Digital Bazaar
Author-email: support@digitalbazaar.com
License: BSD 3-Clause license
Classifier: Development Status :: 4 - Beta
Classifier: Environment :: Console
Classifier: Environment :: Web Environment
Classifier: Intended Audience :: Developers
Classifier: License :: OSI Approved :: BSD License
Classifier: Operating System :: OS Independent
Classifier: Programming Language :: Python
Classifier: Topic :: Internet
Classifier: Topic :: Software Development :: Libraries
License-File: LICENSE
Requires-Dist: cachetools
Requires-Dist: frozendict
Requires-Dist: lxml
Provides-Extra: aiohttp
Requires-Dist: aiohttp ; extra == 'aiohttp'
Provides-Extra: cachetools
Requires-Dist: cachetools ; extra == 'cachetools'
Provides-Extra: frozendict
Requires-Dist: frozendict ; extra == 'frozendict'
Provides-Extra: requests
Requires-Dist: requests ; extra == 'requests'
